{
  "entity": {
    "sensor": {
      "total_count": {
        "default": "mdi:wifi"
      },
      "unknown_count": {
        "default": "mdi:wifi-off"
      },
      "interface": {
        "default": "mdi:lan"
      },
      "last_updated": {
        "default": "mdi:update"
      }
    },
    "binary_sensor": {
      "new_network": {
        "default": "mdi:wifi-check",
        "state": {
          "on": "mdi:wifi-alert",
          "off": "mdi:wifi-check"
        }
      },
      "proximity_alert": {
        "default": "mdi:wifi-strength-4-alert",
        "state": {
          "on": "mdi:wifi-strength-4-alert",
          "off": "mdi:wifi-strength-outline"
        }
      }
    },
    "number": {
      "scan_interval": {
        "default": "mdi:timer-cog-outline"
      }
    },
    "button": {
      "scan_now": {
        "default": "mdi:radar"
      }
    }
  }
}
